[{"title":"dentist","start":"2017-06-23 09:00:00","type":"rdv"},{"title":"docteur","start":"2017-06-22 07:30:00","type":"rdv"},{"title":"","start":"2017-06-24 13:00:00","type":"rdv"},{"title":"Rdv trait importemps","start":"2017-06-24 10:00:00","type":"rdv"},{"title":"Rendez-vous chez le coiffeur","start":"2017-06-23 08:00:00","type":"rdv"},{"title":"","start":"2017-06-22 09:00:00","type":"rdv"},{"title":"","start":"2017-06-23 11:00:00","type":"rdv"},{"title":"","start":"2017-06-22 14:00:00","type":"rdv"},{"title":"","start":"2017-06-19 10:30:00","type":"rdv"},{"title":"","start":"2017-06-24 16:30:00","type":"rdv"},{"title":"","start":"2017-06-22 15:00:00","type":"rdv"},{"title":"","start":"2017-06-22 17:00:00","type":"rdv"},{"title":"","start":"2017-06-21 17:30:00","type":"rdv"},{"title":"faire du th\u00e9 pour rester eveiller","start":"2017-06-22 14:00:00","type":"rdv"},{"title":"th\u00e9","start":"2017-06-22 14:00:00","type":"rdv"}]